{
  "project_info": {
    "project_number": "598865050774",
    "project_id": "ottoogennie",
    "storage_bucket": "ottoogennie.appspot.com"
  },
  "client": [
    {
      "client_info": {
        "mobilesdk_app_id": "1:598865050774:android:413c147a18a2e7598f56b7",
        "android_client_info": {
          "package_name": "com.ottoogennie"
        }
      },
      "oauth_client": [
        {
          "client_id": "598865050774-kdj8h3a8efs3cetcj1ei3u3np15lsg2g.apps.googleusercontent.com",
          "client_type": 1,
          "android_info": {
            "package_name": "com.ottoogennie",
            "certificate_hash": "d2bc11af16c2ef48c854feacdf68b032067b1155"
          }
        },
        {
          "client_id": "598865050774-4gd1t6kr5kg60hnethhru9kdcnedkn1o.apps.googleusercontent.com",
          "client_type": 3
        }
      ],
      "api_key": [
        {
          "current_key": "AIzaSyCLFKbhK4EQd61dn0jCTjbra4s9u-YqZ7k"
        }
      ],
      "services": {
        "appinvite_service": {
          "other_platform_oauth_client": [
            {
              "client_id": "598865050774-4gd1t6kr5kg60hnethhru9kdcnedkn1o.apps.googleusercontent.com",
              "client_type": 3
            }
          ]
        }
      }
    }
  ],
  "configuration_version": "1"
}